[
    {
        "Rule": "ExtraLabelValidation",
        "IgnoreList": [
            {
                "IgnoreText": "<true",
                "Usage":"",
                "Description": "Example: highlight-<true/false>, '<true' , Link: https://learn.microsoft.com/en-us/python/api/azure-search-documents/azure.search.documents.models.querycaptiontype?view=azure-python"
            }
        ]
    },
    {
        "Rule": "UnnecessarySymbolsValidation",
        "IgnoreList": [
            {
                "IgnoreText": "/indexes/",
                "Usage":"prefix",
                "Description": "Example: include /indexes/[index name]/docs for a given index name , Link: https://learn.microsoft.com/en-us/java/api//com.azure.search.documents.searchclient?view=azure-java-stable"
            },
            {
                "IgnoreText": "dist",
                "Usage":"prefix",
                "Description": "Example: dict[str, str] , If the prefix is 'dist' / 'list' / 'optional' ..., the symbol [ is considered meaningful. , Link: https://learn.microsoft.com/en-us/python/api/azure-storage-blob/azure.storage.blob.aio.containerclient?view=azure-python#azure-storage-blob-aio-containerclient-from-connection-string"
            },
            {
                "IgnoreText": "list",
                "Usage":"prefix",
                "Description": "Example: list[RecognizedForm] , Link: https://learn.microsoft.com/en-us/python/api/azure-ai-formrecognizer/azure.ai.formrecognizer.aio.formrecognizerclient?view=azure-python"
            },
            {
                "IgnoreText": "dict",
                "Usage":"prefix",
                "Description": "Example: dict[str, str] , Link: https://learn.microsoft.com/en-us/python/api/azure-ai-formrecognizer/azure.ai.formrecognizer.aio.documentmodeladministrationclient?view=azure-python"
            },
            {
                "IgnoreText": "Union",
                "Usage":"prefix",
                "Description": "Example: Union[str, int] , Link: https://learn.microsoft.com/en-us/python/api/azure-ai-formrecognizer/azure.ai.formrecognizer.aio.formtrainingclient?view=azure-python"
            },
            {
                "IgnoreText": "Literal",
                "Usage":"prefix",
                "Description": "Example: Literal[\"High\", \"Low\"] , Link: https://learn.microsoft.com/en-us/python/api/azure-cosmos/azure.cosmos.aio.containerproxy?view=azure-python"
            },
            {
                "IgnoreText": "Callable",
                "Usage":"prefix",
                "Description": "Example: Callable[[Dict[str, str], Dict[str, Any]], None] , Link: https://learn.microsoft.com/en-us/python/api/azure-cosmos/azure.cosmos.aio.containerproxy?view=azure-python"
            },
            {
                "IgnoreText": "Tuple",
                "Usage":"prefix",
                "Description": "Example: Tuple[Any] , Link: https://learn.microsoft.com/en-us/python/api/azure-cosmos/azure.cosmos.aio.containerproxy?view=azure-python"
            },
            {
                "IgnoreText": "Awaitable",
                "Usage":"prefix",
                "Description": "Example: Awaitable[None] , Link: https://learn.microsoft.com/en-us/python/api/azure-cosmos/azure.cosmos.aio.containerproxy?view=azure-python"
            },
            {
                "IgnoreText": "Optional",
                "Usage":"prefix",
                "Description": "Example: Optional[int] , Link: https://learn.microsoft.com/en-us/python/api/azure-storage-blob/azure.storage.blob.aio.blobclient?view=azure-python"
            },
            {
                "IgnoreText": "\"",
                "Usage":"prefix",
                "Description": "Example: \"[scope:][type]:[id]\" , If the prefix is ':' / ':' / ':]' ..., the symbol [ is considered meaningful."
            },
            {
                "IgnoreText": ":",
                "Usage":"prefix",
                "Description": "Example: \"[scope:][type]:[id]\" , If the prefix is ':' / ':' / ':]' ..., the symbol [ is considered meaningful."
            },
            {
                "IgnoreText": ":]",
                "Usage":"prefix",
                "Description": "Example: \"[scope:][type]:[id]\" , If the prefix is ':' / ':' / ':]' ..., the symbol [ is considered meaningful."
            },
            {
                "IgnoreText": "port",
                "Usage":"content",
                "Description": "Example:{protocol}://{fully-qualified-domain-name}[:{port#}] , Link: https://learn.microsoft.com/en-us/python/api/azure-search-documents/azure.search.documents.indexes.models.corsoptions?view=azure-python" 
            },
            {
                "IgnoreText": " str",
                "Usage":"content",
                "Description": "Example: dict[str, str] , If the prefix is 'str' / 'int' ..., the symbol [ is considered meaningful. , Link: https://learn.microsoft.com/en-us/python/api/azure-storage-blob/azure.storage.blob.aio.containerclient?view=azure-python#azure-storage-blob-aio-containerclient-from-connection-string"
            },
            {
                "IgnoreText": "str,",
                "Usage":"content",
                "Description": "Example: Union[bytes, str, Iterable[AnyStr] , Link: https://learn.microsoft.com/en-us/python/api/azure-storage-blob/azure.storage.blob.aio.containerclient?view=azure-python "
            },
            {
                "IgnoreText": "int,",
                "Usage":"content",
                "Description": "Example: Callable[[int, int], None] , Link: https://learn.microsoft.com/en-us/python/api/azure-storage-blob/azure.storage.blob.blobclient?view=azure-python"
            },
            {
                "IgnoreText": " int",
                "Usage":"content",
                "Description": "Example: Callable[[int, int], None] , Link: https://learn.microsoft.com/en-us/python/api/azure-storage-blob/azure.storage.blob.blobclient?view=azure-python"
            },
            {
                "IgnoreText": " or ",
                "Usage":"content",
                "Description": "Example: List[KeyOperation or str] , Link: https://learn.microsoft.com/en-us/python/api/azure-keyvault-keys/azure.keyvault.keys.keyclient?view=azure-python"
            },
            {
                "IgnoreText": "None",
                "Usage":"content",
                "Description": "Example: Optional[Callable[[str], None]], Link: https://learn.microsoft.com/en-us/python/api/azure-storage-blob/azure.storage.blob?view=azure-python"
            },
            {
                "IgnoreText": "...",
                "Usage":"content",
                "Description": "Example: sleep for [0.0s, 0.2s, 0.4s, ...] "
            },
            {
                "IgnoreText": "0.0",
                "Usage":"content",
                "Description": "Example:  Value is between [0.0, 1.0], Link: https://learn.microsoft.com/en-us/python/api/azure-ai-formrecognizer/azure.ai.formrecognizer.formword?view=azure-python "
            },
            {
                "IgnoreText": "list",
                "Usage":"content",
                "Description": "Example: AsyncLROPoller[list[RecognizedForm]] , Link: https://learn.microsoft.com/en-us/python/api/azure-ai-formrecognizer/azure.ai.formrecognizer.aio.formrecognizerclient?view=azure-python"
            },
            {
                "IgnoreText": ",",
                "Usage":"content",
                "Description": "Example: like pages=[\"1-3\", \"5-6\"] , Link: https://learn.microsoft.com/en-us/python/api/azure-ai-formrecognizer/azure.ai.formrecognizer.aio.formrecognizerclient?view=azure-python"
            }
        ]
    },
    {
        "Rule": "GarbledTextValidation",
        "IgnoreList": [
            {
                "IgnoreText": ":mm:",
                "Usage":"",
                "Description": "specified in the format 'hh:mm:ss', ':mm:' , Link: https://learn.microsoft.com/en-us/python/api/azure-search-documents/azure.search.documents.indexes.models.indexingparametersconfiguration?view=azure-python"
            },
            {
                "IgnoreText": ":05:",
                "Usage":"",
                "Description": "specified in the format 'hh:mm:ss'.Default value: 00:05:00, '05' , Link: https://learn.microsoft.com/en-us/python/api/azure-search-documents/azure.search.documents.indexes.models.indexingparametersconfiguration?view=azure-python"
            },
            {
                "IgnoreText": ":10:",
                "Usage":"",
                "Description": "Date: Fri, 19 May 2023 17:10:33 GMT, ':10:' , Link: https://learn.microsoft.com/en-us/python/api/overview/azure/storage?view=azure-python"
            },
            {
                "IgnoreText": ":00:",
                "Usage":"",
                "Description": "2020-02-20 00:00:00, ':00:' , Link: https://learn.microsoft.com/en-us/python/api/azure-ai-language-conversations/azure.ai.language.conversations.aio.conversationanalysisclient?view=azure-python&branch=main"
            },
            {
                "IgnoreText": ":24:",
                "Usage":"",
                "Description": " for example, 2015-01-28T16:24:48.789Z., ':24:' , Link: https://learn.microsoft.com/en-us/python/api/azure-iot-hub/azure.iot.hub.protocol.models.twin(class)?view=azure-python&branch=main"
            },
            {
                "IgnoreText": ":51:",
                "Usage":"",
                "Description": "2021-12-08T23:51:14.1104269Z, ':51:' , Link: https://learn.microsoft.com/en-us/python/api/overview/azure/monitor-ingestion-readme?view=azure-python"
            }
        ]
    }

]