[
  {
    "PackageName": "packageD",
    "ResultList": [
      {
        "NO.": 1,
        "ErrorInfo": "Extra label found: <xref",
        "NumberOfOccurrences": 21,
        "LocationsOfErrors": [
          "1. Appears 21 times , label : <xref ",
          "2. Appears 21 times , label : <xref ",
          "3. Appears 21 times , label : <xref "
        ],
        "ErrorLink": "https://learn.microsoft.com/en-us/python/api/azure-search-documents/azure.search.documents.indexes.aio.searchindexerclient?view=azure-python",
        "TestCase": "TestExtraLabel",
        "AdditionalNotes": null
      },
      {
        "NO.": 1,
        "ErrorInfo": "Extra label found: <xref",
        "NumberOfOccurrences": 21,
        "LocationsOfErrors": [
          "1. Appears 21 times , label : <xref ",
          "2. Appears 21 times , label : <xref ",
          "3. Appears 21 times , label : <xref "
        ],
        "ErrorLink": "https://learn.microsoft.com/en-us/python/api/azure-search-documents/azure.search.documents.indexes.aio.searchindexerclient?view=azure-python",
        "TestCase": "TestExtraLabel",
        "AdditionalNotes": null
      }
    ],
    "Note": null
  },
  {
    "PackageName": "packageB",
    "ResultList": [
      {
        "NO.": 1,
        "ErrorInfo": "Extra label found: <xref",
        "NumberOfOccurrences": 21,
        "LocationsOfErrors": [
          "1. Appears 21 times , label : <xref ",
          "2. Appears 21 times , label : <xref ",
          "3. Appears 21 times , label : <xref "
        ],
        "ErrorLink": "https://learn.microsoft.com/en-us/python/api/azure-search-documents/azure.search.documents.indexes.aio.searchindexerclient?view=azure-python",
        "TestCase": "TestExtraLabel",
        "AdditionalNotes": null
      }
    ],
    "Note": null
  },
  {
    "PackageName": "packageC",
    "ResultList": [
      {
        "NO.": 1,
        "ErrorInfo": "Extra label found: <xref",
        "NumberOfOccurrences": 21,
        "LocationsOfErrors": [
          "1. Appears 21 times , label : <xref ",
          "2. Appears 21 times , label : <xref ",
          "3. Appears 21 times , label : <xref "
        ],
        "ErrorLink": "https://learn.microsoft.com/en-us/python/api/azure-search-documents/azure.search.documents.indexes.aio.searchindexerclient?view=azure-python",
        "TestCase": "TestExtraLabel",
        "AdditionalNotes": null
      }
    ],
    "Note": null
  },
  {
    "PackageName": "packageA",
    "ResultList": [
      {
        "NO.": 1,
        "ErrorInfo": "Unnecessary symbols found: ~",
        "NumberOfOccurrences": 6,
        "LocationsOfErrors": [
          "1. Appears 6 times ,  Unnecessary symbol: ~ in code: as_dict(keep_readonly: bool = True, key_transformer: ~typing.Callable[[str, ~typing.Dict[str, ~typing.Any], ~typing.Any], ~typing.Any] = <function attribute_transformer>, **kwargs: ~typing.Any) -> MutableMapping[str, Any]"
        ],
        "ErrorLink": "https://learn.microsoft.com/en-us/python/api/azure-appconfiguration/azure.appconfiguration.featureflagconfigurationsetting?view=azure-python",
        "TestCase": "TestUnnecessarySymbols",
        "AdditionalNotes": null
      },
      {
        "NO.": 2,
        "ErrorInfo": "Unnecessary symbols found: ~",
        "NumberOfOccurrences": 6,
        "LocationsOfErrors": [
          "1. Appears 6 times ,  Unnecessary symbol: ~ in code: as_dict(keep_readonly: bool = True, key_transformer: ~typing.Callable[[str, ~typing.Dict[str, ~typing.Any], ~typing.Any], ~typing.Any] = <function attribute_transformer>, **kwargs: ~typing.Any) -> MutableMapping[str, Any]"
        ],
        "ErrorLink": "https://learn.microsoft.com/en-us/python/api/azure-appconfiguration/azure.appconfiguration.secretreferenceconfigurationsetting?view=azure-python",
        "TestCase": "TestUnnecessarySymbols",
        "AdditionalNotes": null
      }
    ],
    "Note": null
  }
]